flowspec_exporter/__init__.py
flowspec_exporter/exporter.py
flowspec_exporter/flowspec.py
flowspec_exporter/main.py
flowspec_exporter/parser.py
flowspec_exporter/worker.py
flowspec_exporter/routers/__init__.py
flowspec_exporter/routers/cisco_ios.py
flowspec_exporter/routers/huawei_vrp.py
flowspec_exporter/routers/juniper_junos.py
flowspec_exporter-0.1.2.dist-info/licenses/LICENSE
flowspec_exporter-0.1.2.dist-info/METADATA
flowspec_exporter-0.1.2.dist-info/WHEEL
flowspec_exporter-0.1.2.dist-info/top_level.txt
flowspec_exporter-0.1.2.dist-info/RECORD
