Metadata-Version: 2.4
Name: flowspec_exporter
Version: 0.1.2
Summary: Add your description here
Requires-Python: >=3.13
License-File: LICENSE
Requires-Dist: netaddr>=1.3.0
Requires-Dist: asyncssh>=2.20.0
Requires-Dist: dataclasses-json>=0.6.7
Provides-Extra: all
Requires-Dist: python-json-logger>=3.2.1; extra == "all"
Requires-Dist: pytimeparse>=1.1.8; extra == "all"
Requires-Dist: tenacity>=9.0.0; extra == "all"
Requires-Dist: asyncpg>=0.30.0; extra == "all"
Requires-Dist: prometheus-client>=0.23.1; extra == "all"
Requires-Dist: fastapi[standard-no-fastapi-cloud-cli]>=0.118.0; extra == "all"
Dynamic: license-file
